incached/__init__.py
incached/cache.py
incached/exceptions.py
incached/utils.py
incached-1.3.dist-info/LICENSE
incached-1.3.dist-info/METADATA
incached-1.3.dist-info/WHEEL
incached-1.3.dist-info/top_level.txt
incached-1.3.dist-info/RECORD
