Metadata-Version: 2.1
Name: incached
Version: 1.3
Summary: Caching engine for python
Home-page: https://gitlab.com/cytedge/incached
Author: Cytedge
Author-email: cytedge@wnhm.tech
License: UNKNOWN
Platform: UNKNOWN
Classifier: Programming Language :: Python :: 3
Classifier: License :: OSI Approved :: MIT License
Classifier: Operating System :: OS Independent
Requires-Python: >=3.6
